{
  "info": {
    "_postman_id": "fc104bc4-8c6d-4f8b-816d-f6d1415076bb",
    "name": "Hillel_Task_5",
    "schema": "https://schema.getpostman.com/json/collection/v2.1.0/collection.json"
  },
  "item": [
    {
      "name": "http://localhost:8096/com.hillel.task_5/client",
      "request": {
        "method": "POST",
        "header": [
          {
            "key": "Accept",
            "value": "application/json",
            "type": "text"
          }
        ],
        "body": {
          "mode": "raw",
          "raw": "{\n\t\"clientName\":\"Anton\"\n}",
          "options": {
            "raw": {
              "language": "json"
            }
          }
        },
        "url": {
          "raw": "http://localhost:8096/com.hillel.task_5/client",
          "protocol": "http",
          "host": [
            "localhost"
          ],
          "port": "8096",
          "path": [
            "com.hillel.task_5",
            "client"
          ]
        }
      },
      "response": []
    },
    {
      "name": "http://localhost:8096/com.hillel.task_5/client",
      "protocolProfileBehavior": {
        "disableBodyPruning": true
      },
      "request": {
        "method": "GET",
        "header": [
          {
            "key": "Accept",
            "value": "application/json",
            "type": "text"
          },
          {
            "key": "Content-Type",
            "name": "Content-Type",
            "value": "application/json",
            "type": "text"
          }
        ],
        "body": {
          "mode": "raw",
          "raw": "{\n    \"clientId\": \"2\"\n}",
          "options": {
            "raw": {
              "language": "json"
            }
          }
        },
        "url": {
          "raw": "http://localhost:8096/com.hillel.task_5/client",
          "protocol": "http",
          "host": [
            "localhost"
          ],
          "port": "8096",
          "path": [
            "com.hillel.task_5",
            "client"
          ]
        }
      },
      "response": []
    },
    {
      "name": "http://localhost:8096/com.hillel.task_5/client",
      "request": {
        "method": "PUT",
        "header": [
          {
            "key": "Accept",
            "value": "application/json",
            "type": "text"
          },
          {
            "key": "Content-Type",
            "name": "Content-Type",
            "value": "application/json",
            "type": "text"
          }
        ],
        "body": {
          "mode": "raw",
          "raw": "{\n    \"clientId\": \"3\",\n    \"clientName\":\"Andrew\"\n}",
          "options": {
            "raw": {
              "language": "json"
            }
          }
        },
        "url": {
          "raw": "http://localhost:8096/com.hillel.task_5/client",
          "protocol": "http",
          "host": [
            "localhost"
          ],
          "port": "8096",
          "path": [
            "com.hillel.task_5",
            "client"
          ],
          "query": [
            {
              "key": "",
              "value": ""
            }
          ]
        }
      },
      "response": []
    },
    {
      "name": "http://localhost:8096/com.hillel.task_5/client",
      "request": {
        "method": "DELETE",
        "header": [
          {
            "key": "Accept",
            "value": "application/json",
            "type": "text"
          },
          {
            "key": "Content-Type",
            "name": "Content-Type",
            "value": "application/json",
            "type": "text"
          }
        ],
        "body": {
          "mode": "raw",
          "raw": "{\n    \"clientId\": \"2\"\n}",
          "options": {
            "raw": {
              "language": "json"
            }
          }
        },
        "url": {
          "raw": "http://localhost:8096/com.hillel.task_5/client",
          "protocol": "http",
          "host": [
            "localhost"
          ],
          "port": "8096",
          "path": [
            "com.hillel.task_5",
            "client"
          ]
        }
      },
      "response": []
    },
    {
      "name": "http://localhost:8096/com.hillel.task_5/client/account",
      "request": {
        "method": "PUT",
        "header": [
          {
            "key": "Accept",
            "value": "application/json",
            "type": "text"
          },
          {
            "key": "Content-Type",
            "name": "Content-Type",
            "value": "application/json",
            "type": "text"
          }
        ],
        "body": {
          "mode": "raw",
          "raw": "{\n\t\"clientId\":\"1\",\n\t\"currency\":\"USD\",\n\t\"balance\":\"106\"\n}",
          "options": {
            "raw": {
              "language": "json"
            }
          }
        },
        "url": {
          "raw": "http://localhost:8096/com.hillel.task_5/client/account",
          "protocol": "http",
          "host": [
            "localhost"
          ],
          "port": "8096",
          "path": [
            "com.hillel.task_5",
            "client",
            "account"
          ]
        }
      },
      "response": []
    },
    {
      "name": "http://localhost:8096/com.hillel.task_5/client/account",
      "request": {
        "method": "DELETE",
        "header": [
          {
            "key": "Accept",
            "value": "application/json",
            "type": "text"
          },
          {
            "key": "Content-Type",
            "name": "Content-Type",
            "value": "application/json",
            "type": "text"
          }
        ],
        "body": {
          "mode": "raw",
          "raw": "{\n\t\"clientId\":\"1\"\n}",
          "options": {
            "raw": {
              "language": "json"
            }
          }
        },
        "url": {
          "raw": "http://localhost:8096/com.hillel.task_5/client/account",
          "protocol": "http",
          "host": [
            "localhost"
          ],
          "port": "8096",
          "path": [
            "com.hillel.task_5",
            "client",
            "account"
          ]
        }
      },
      "response": []
    },
    {
      "name": "http://localhost:8096/com.hillel.task_5/client/account",
      "request": {
        "method": "POST",
        "header": [
          {
            "key": "Accept",
            "value": "application/json",
            "type": "text"
          },
          {
            "key": "Content-Type",
            "name": "Content-Type",
            "value": "application/json",
            "type": "text"
          }
        ],
        "body": {
          "mode": "raw",
          "raw": "{\n\t\"clientId\":\"1\",\n\t\"currency\":\"USD\",\n\t\"balance\":\"110\"\n}",
          "options": {
            "raw": {
              "language": "json"
            }
          }
        },
        "url": {
          "raw": "http://localhost:8096/com.hillel.task_5/client/account",
          "protocol": "http",
          "host": [
            "localhost"
          ],
          "port": "8096",
          "path": [
            "com.hillel.task_5",
            "client",
            "account"
          ]
        }
      },
      "response": []
    },
    {
      "name": "http://localhost:8096/com.hillel.task_5/client/account",
      "protocolProfileBehavior": {
        "disableBodyPruning": true
      },
      "request": {
        "method": "GET",
        "header": [
          {
            "key": "Accept",
            "value": "application/json",
            "type": "text"
          },
          {
            "key": "Content-Type",
            "name": "Content-Type",
            "value": "application/json",
            "type": "text"
          }
        ],
        "body": {
          "mode": "raw",
          "raw": "{\n\t\"clientId\":\"1\"\n}",
          "options": {
            "raw": {
              "language": "json"
            }
          }
        },
        "url": {
          "raw": "http://localhost:8096/com.hillel.task_5/client/account",
          "protocol": "http",
          "host": [
            "localhost"
          ],
          "port": "8096",
          "path": [
            "com.hillel.task_5",
            "client",
            "account"
          ]
        }
      },
      "response": []
    }
  ],
  "protocolProfileBehavior": {}
}